LICENSE
MANIFEST.in
README.md
VERSION
setup.cfg
setup.py
src/cltl.reply_generation.egg-info/PKG-INFO
src/cltl.reply_generation.egg-info/SOURCES.txt
src/cltl.reply_generation.egg-info/dependency_links.txt
src/cltl.reply_generation.egg-info/requires.txt
src/cltl.reply_generation.egg-info/top_level.txt
src/cltl/combot/backend/api/discrete.py
src/cltl/combot/backend/utils/casefolding.py
src/cltl/combot/backend/utils/triple_helpers.py
src/cltl/reply_generation/__init__.py
src/cltl/reply_generation/api.py
src/cltl/reply_generation/lenka_replier.py
src/cltl/reply_generation/nsp_replier.py
src/cltl/reply_generation/rl_replier.py
src/cltl/reply_generation/data/animations.py
src/cltl/reply_generation/data/base_cases.py
src/cltl/reply_generation/data/cfg.txt
src/cltl/reply_generation/data/lexicon.json
src/cltl/reply_generation/data/sentences.py
src/cltl/reply_generation/next_sentence_prediction/__init__.py
src/cltl/reply_generation/next_sentence_prediction/nsp.py
src/cltl/reply_generation/reinforcement_learning/__init__.py
src/cltl/reply_generation/reinforcement_learning/rl.py
src/cltl/reply_generation/utils/__init__.py
src/cltl/reply_generation/utils/helper_functions.py
src/cltl/reply_generation/utils/replier_utils.py
src/cltl/reply_generation/utils/wordnet_utils.py