Metadata-Version: 2.1
Name: cltl.reply-generation
Version: 0.0.dev9
Summary: The Leolani Language module for reply generation
Home-page: https://github.com/leolani/cltl-languagegeneration
License: MIT License
Platform: UNKNOWN
Requires-Python: >=3.7
License-File: LICENSE
